odoo/addons/delivery_carrier_max_weight_constraint/README.rst
odoo/addons/delivery_carrier_max_weight_constraint/__init__.py
odoo/addons/delivery_carrier_max_weight_constraint/__manifest__.py
odoo/addons/delivery_carrier_max_weight_constraint/i18n/delivery_carrier_max_weight_constraint.pot
odoo/addons/delivery_carrier_max_weight_constraint/i18n/es.po
odoo/addons/delivery_carrier_max_weight_constraint/i18n/it.po
odoo/addons/delivery_carrier_max_weight_constraint/i18n/nl.po
odoo/addons/delivery_carrier_max_weight_constraint/i18n/nl_NL.po
odoo/addons/delivery_carrier_max_weight_constraint/models/__init__.py
odoo/addons/delivery_carrier_max_weight_constraint/models/delivery_carrier.py
odoo/addons/delivery_carrier_max_weight_constraint/models/res_company.py
odoo/addons/delivery_carrier_max_weight_constraint/models/res_config_settings.py
odoo/addons/delivery_carrier_max_weight_constraint/models/stock_package_type.py
odoo/addons/delivery_carrier_max_weight_constraint/readme/CONTRIBUTORS.rst
odoo/addons/delivery_carrier_max_weight_constraint/readme/DESCRIPTION.rst
odoo/addons/delivery_carrier_max_weight_constraint/readme/USAGE.rst
odoo/addons/delivery_carrier_max_weight_constraint/static/description/icon.png
odoo/addons/delivery_carrier_max_weight_constraint/static/description/index.html
odoo/addons/delivery_carrier_max_weight_constraint/tests/__init__.py
odoo/addons/delivery_carrier_max_weight_constraint/tests/test_max_weight_constraint.py
odoo/addons/delivery_carrier_max_weight_constraint/views/delivery_carrier_views.xml
odoo/addons/delivery_carrier_max_weight_constraint/views/res_config_settings_views.xml
odoo/addons/delivery_carrier_max_weight_constraint/views/stock_package_type_views.xml
odoo/addons/delivery_carrier_max_weight_constraint/wizards/__init__.py
odoo/addons/delivery_carrier_max_weight_constraint/wizards/choose_delivery_package.py
odoo_addon_delivery_carrier_max_weight_constraint-16.0.1.0.1.8.dist-info/METADATA
odoo_addon_delivery_carrier_max_weight_constraint-16.0.1.0.1.8.dist-info/WHEEL
odoo_addon_delivery_carrier_max_weight_constraint-16.0.1.0.1.8.dist-info/top_level.txt
odoo_addon_delivery_carrier_max_weight_constraint-16.0.1.0.1.8.dist-info/RECORD
